CodeLibWrapper.py
License.txt
MANIFEST.in
Package.bat
README.txt
Readme.txt
Uninstall.bat
Upgrade.bat
__init__.py
requirements.txt
setup.py
.idea/CodeLibWrapper.iml
.idea/codeStyleSettings.xml
.idea/encodings.xml
.idea/misc.xml
.idea/modules.xml
.idea/vcs.xml
.idea/dictionaries/bzhou.xml
.idea/inspectionProfiles/Project_Default.xml
.idea/inspectionProfiles/profiles_settings.xml
MorningstarAutoTestingFramework.egg-info/PKG-INFO
MorningstarAutoTestingFramework.egg-info/SOURCES.txt
MorningstarAutoTestingFramework.egg-info/dependency_links.txt
MorningstarAutoTestingFramework.egg-info/requires.txt
MorningstarAutoTestingFramework.egg-info/top_level.txt
PythonStudyCase/DateTimeHelper.py
PythonStudyCase/Scheduler.py
PythonStudyCase/__init__.py
PythonStudyCase/temp_demo.py
RobotFrameworkSample/__init__.py
RobotFrameworkSample/geckodriver.log
RobotFrameworkSample/SampleData/2014-11-30.xml
RobotFrameworkSample/SampleData/Id.txt
RobotFrameworkSample/SampleData/Sample_EnvironmentConfig.xml
RobotFrameworkSample/SampleData/Test.xml
RobotFrameworkSample/SampleData/bigfile.xml
RobotFrameworkSample/SampleData/pandas_csv.csv
RobotFrameworkSample/SimpleUsageTutorials/BasicBuiltInLibrarySample_BuiltInKeyword.txt
RobotFrameworkSample/SimpleUsageTutorials/BasicBuiltInLibrarySample_Collections.txt
RobotFrameworkSample/SimpleUsageTutorials/BasicBuiltInLibrarySample_DateTime.txt
RobotFrameworkSample/SimpleUsageTutorials/BasicBuiltInLibrarySample_Dialogs.txt
RobotFrameworkSample/SimpleUsageTutorials/BasicBuiltInLibrarySample_OperatingSystem.txt
RobotFrameworkSample/SimpleUsageTutorials/BasicBuiltInLibrarySample_Process.txt
RobotFrameworkSample/SimpleUsageTutorials/BasicBuiltInLibrarySample_Screenshot.txt
RobotFrameworkSample/SimpleUsageTutorials/BasicBuiltInLibrarySample_String.txt
RobotFrameworkSample/SimpleUsageTutorials/BasicBuiltInLibrarySample_Telnet.txt
RobotFrameworkSample/SimpleUsageTutorials/BasicBuiltInLibrarySample_XML.txt
RobotFrameworkSample/SimpleUsageTutorials/BasicDataType.txt
RobotFrameworkSample/SimpleUsageTutorials/BasicRobotFrameworkOperation.txt
RobotFrameworkSample/SimpleUsageTutorials/Pandas.txt
RobotFrameworkSample/UserKeywordTestSuite/Suite_API.txt
RobotFrameworkSample/UserKeywordTestSuite/Suite_AboutMe.txt
