Metadata-Version: 1.0
Name: MorningstarAutoTestingFramework
Version: 0.1.2
Summary: Robot Framework util package for Morningstar DataProduct/API team.
Home-page: https://pypi.python.org/pypi/MorningstarAutoTestingFramework
Author: Benjamin Zhou
Author-email: Benjamin.Zhou@morningstar.com
License: All Data Production/API QA team member use.
Keywords: Data Production,API,Robot Framework
Platform: Python & Robot framework
